mseep_holoviz_mcp-1.0.0.dist-info/licenses/LICENSE.txt
tests/__init__.py
tests/test_docs_mcp.py
tests/test_docs_mcp_reference_guide.py
tests/test_panel_mcp.py
tests/test_server.py
tests/docs_mcp/__init__.py
tests/docs_mcp/test_data.py
tests/panel_mcp/__init__.py
tests/panel_mcp/test_data.py
tests/ui/__init__.py
tests/ui/test_ui.py
mseep_holoviz_mcp-1.0.0.dist-info/METADATA
mseep_holoviz_mcp-1.0.0.dist-info/WHEEL
mseep_holoviz_mcp-1.0.0.dist-info/top_level.txt
mseep_holoviz_mcp-1.0.0.dist-info/RECORD
