Metadata-Version: 2.4
Name: mseep-holoviz-mcp
Version: 1.0.0
Summary: A Model Context Protocol (MCP) server for the HoloViz ecosystem
Home-page: https://github.com/mseep
Author: mseep
Author-email: support@skydeck.ai
Maintainer: mseep
Maintainer-email: support@skydeck.ai
Keywords: mseep
Classifier: Programming Language :: Python :: 3
Classifier: License :: OSI Approved :: MIT License
Classifier: Operating System :: OS Independent
Requires-Python: >=3.6
License-File: LICENSE.txt
Requires-Dist: certifi
Requires-Dist: chromadb
Requires-Dist: fastmcp
Requires-Dist: GitPython
Requires-Dist: packaging
Requires-Dist: nbconvert
Requires-Dist: panel
Requires-Dist: sentence-transformers
Dynamic: author
Dynamic: author-email
Dynamic: classifier
Dynamic: description
Dynamic: description-content-type
Dynamic: home-page
Dynamic: keywords
Dynamic: license-file
Dynamic: maintainer
Dynamic: maintainer-email
Dynamic: requires-dist
Dynamic: requires-python
Dynamic: summary
